intvert/__init__.py
intvert/invert.py
intvert/sample.py
intvert-0.1.0.dist-info/licenses/LICENSE
intvert-0.1.0.dist-info/METADATA
intvert-0.1.0.dist-info/WHEEL
intvert-0.1.0.dist-info/top_level.txt
intvert-0.1.0.dist-info/RECORD
