Metadata-Version: 2.4
Name: intvert
Version: 0.1.0
Summary: A package for inversion of integer signals from sampled DFT coefficients.
Author-email: Isaac Viviano <16isaac.viviano@gmail.com>
License-Expression: MIT
Project-URL: Homepage, https://github.com/iviviano/intvert
Project-URL: Issues, https://github.com/iviviano/intvert/issues
Project-URL: Documentation, https://intvert.readthedocs.io/en/latest/
Classifier: Programming Language :: Python :: 3
Classifier: Operating System :: OS Independent
Requires-Python: >=3.9
License-File: LICENSE
Requires-Dist: numpy
Requires-Dist: sympy
Requires-Dist: gmpy2
Requires-Dist: fpylll
Requires-Dist: cysignals
Dynamic: license-file
